LAB 06 jkFlipFlop/jk.vhdl
library ieee;
use ieee.std_logic_1164.all;

entity jk is
port(
    J,K,CLK,RST: in std_logic;
    Q,Qb:out    std_logic
    );
end jk;

architecture jk_arch of jk is
begin
    process(J,K,CLK,RST) is
    variable output: std_logic := '0';
    begin
        if (RST = '1') then
            output := '0';
        elsif (rising_edge(CLK)) then
            if(J /= K) then
                output := J;
            elsif (J = '1' and K = '1') then
                output := not output;
            end if;
        end if;
        Q <= output;
        Qb <= not output;
    end process;
end jk_arch;

jk/jk_tb.vhdl
library ieee;
use ieee.std_logic_1164.all;
use ieee.numeric_std.all;

entity testbench is
end testbench;

architecture test of testbench is
signal J,K,CLK,RST: std_logic := '0';
signal Q,Qb: std_logic;

component jk is
port(
    J,K,CLK,RST: in std_logic;
    Q,Qb: out std_logic
    );
end component;

begin
    UUT: jk
    port map(J => J, K => K, CLK => CLK, RST => RST , Q => Q, Qb => Qb);

clock_process: process
begin
    CLK <= '0';
    wait for 10 ns;

    CLK <= '1';
    wait for 10 ns;
end process clock_process;

stimulus_process: process
begin
    RST <= '1';
    wait for 1 ns;

    RST <= '0';
    wait for 1 ns;

    -- test case 1
    J <= '0';
    K <= '0';
    wait for 3 ns;

    -- test case 2
    J <= '0';
    K <= '1';
    wait for 3 ns;

    -- test case 3
    J <= '1';
    K <= '0';
    wait for 3 ns;

    -- test case 4
    J <= '1';
    K <= '1';
    wait for 3 ns;

    wait;
end process stimulus_process;
end test;

LAB 06 - jkFlipFlop/jk_tb.vcd
$date
  Tue Feb 20 20:47:31 2024
$end
$version
  GHDL v0
$end
$timescale
  1 fs
$end
$scope module standard $end
$upscope $end
$scope module std_logic_1164 $end
$upscope $end
$scope module numeric_std $end
$upscope $end
$scope module testbench $end
$var reg 1 ! j $end
$var reg 1 " k $end
$var reg 1 # clk $end
$var reg 1 $ rst $end
$var reg 1 % q $end
$var reg 1 & qb $end
$scope module uut $end
$var reg 1 ' j $end
$var reg 1 ( k $end
$var reg 1 ) clk $end
$var reg 1 * rst $end
$var reg 1 + q $end
$var reg 1 , qb $end
$upscope $end
$upscope $end
$enddefinitions $end
#0
0!
0"
0#
1$
0%
1&
0'
0(
0)
1*
0+
1,
#1000000
0$
0*
#2000000
#5000000
1"
1(
#8000000
1!
0"
1'
0(
#10000000
1#
1%
0&
1)
1+
0,
#11000000
1"
1(
#14000000
#20000000
0#
0)
#30000000
1#
0%
1&
1)
0+
1,
#40000000
0#
0)
#50000000
1#
1%
0&
1)
1+
0,
#60000000
0#
0)
#70000000
1#
0%
1&
1)
0+
1,
#80000000
0#
0)
#90000000
1#
1%
0&
1)
1+
0,
